mojap_airflow_tools/__init__.py
mojap_airflow_tools/constants.py
mojap_airflow_tools/operators.py
mojap_airflow_tools-2.4.3.4.dist-info/METADATA
mojap_airflow_tools-2.4.3.4.dist-info/WHEEL
mojap_airflow_tools-2.4.3.4.dist-info/RECORD
